README.md
setup.py
data/uri-schemes-1.csv
script/make_keys.py
script/testtool.py
src/otest/__init__.py
src/otest/check.py
src/otest/comhandler.py
src/otest/common.py
src/otest/conf_setup.py
src/otest/conf_setup_old.py
src/otest/conversation.py
src/otest/events.py
src/otest/flow.py
src/otest/func.py
src/otest/handling.py
src/otest/interaction.py
src/otest/jlog.py
src/otest/jsonconv.py
src/otest/operation.py
src/otest/parse_cnf.py
src/otest/proc.py
src/otest/prof_util.py
src/otest/result.py
src/otest/session.py
src/otest/shannon_entropy.py
src/otest/summation.py
src/otest/test_setup.py
src/otest/time_util.py
src/otest/tool.py
src/otest/utils.py
src/otest/verify.py
src/otest.egg-info/PKG-INFO
src/otest.egg-info/SOURCES.txt
src/otest.egg-info/dependency_links.txt
src/otest.egg-info/not-zip-safe
src/otest.egg-info/requires.txt
src/otest.egg-info/top_level.txt
src/otest/aus/__init__.py
src/otest/aus/app.py
src/otest/aus/check.py
src/otest/aus/client.py
src/otest/aus/handling.py
src/otest/aus/handling_ph.py
src/otest/aus/operation.py
src/otest/aus/prof_util.py
src/otest/aus/request.py
src/otest/aus/tool.py
src/otest/aus/utils.py
src/otest/aus/preproc/__init__.py
src/otest/aus/preproc/flow_list.py
src/otest/aus/preproc/logs.py
src/otest/aus/preproc/profile.py
src/otest/aus/preproc/testinfo.py
src/otest/contenthandler/__init__.py
src/otest/rp/__init__.py
src/otest/rp/check.py
src/otest/rp/display.py
src/otest/rp/endpoints.py
src/otest/rp/handling.py
src/otest/rp/operation.py
src/otest/rp/parse_conf.py
src/otest/rp/provider.py
src/otest/rp/response.py
src/otest/rp/setup.py
src/otest/rp/tool.py