Metadata-Version: 1.1
Name: otest
Version: 0.7.5
Summary: Basic Test framework for testing OAuth2/OIDC Authorization server and relaying party implementations
Home-page: UNKNOWN
Author: Roland Hedberg
Author-email: roland@catalogix.se
License: Apache 2.0
Platform: UNKNOWN
Classifier: Development Status :: 4 - Beta
Classifier: License :: OSI Approved :: Apache Software License
Classifier: Programming Language :: Python :: 3.5
Classifier: Topic :: Software Development :: Libraries :: Python Modules
